{
  "heroes": {
    "Ana": {
      "sprays": [
        "A97",
        "A95",
        "AB4",
        "AB6",
        "A99",
        "AB9",
        "A9D",
        "ABA",
        "A9C",
        "AA7",
        "AA2",
        "AA3",
        "B2B",
        "AB5",
        "A94",
        "A9F",
        "AA0",
        "1196",
        "AB8",
        "A9A",
        "AA5",
        "AB7",
        "AA1",
        "1594",
        "A98",
        "A9B",
        "AB3",
        "B7A",
        "C52",
        "D27",
        "D09",
        "D59",
        "EDA",
        "106D",
        "106F"
      ],
      "weapons": [
        "A67",
        "A68"
      ],
      "skins": [
        "A73",
        "ADA",
        "ADB",
        "ADC",
        "AD9",
        "AD7",
        "AD8",
        "C4F",
        "E5F",
        "1564",
        "1766",
        "1561",
        "1765",
        "155B",
        "1762",
        "1549",
        "175C",
        "13DA",
        "1763",
        "154F",
        "1760",
        "1555",
        "175D",
        "1558",
        "175E",
        "167C",
        "1699",
        "155E",
        "1764",
        "154C",
        "175F",
        "1546",
        "1758",
        "1552",
        "1761",
        "ADD",
        "ADE",
        "AE0",
        "ADF",
        "E5C",
        "1245"
      ],
      "poses": [
        "A59",
        "A76",
        "A74",
        "A75",
        "C35",
        "D01",
        "EB1"
      ],
      "highlight-intros": [
        "A5A",
        "A7A",
        "A7B",
        "A7D",
        "1271"
      ],
      "voice-lines": [
        "A5C",
        "A5E",
        "15C9",
        "A64",
        "A66",
        "A62",
        "A60",
        "A61",
        "A5F",
        "A5D",
        "A63",
        "A65",
        "1216",
        "BC7",
        "C91",
        "12B1",
        "1332",
        "D7E",
        "1628",
        "E93",
        "10C1",
        "10C2",
        "1908",
        "10FC",
        "10FB"
      ],
      "emotes": [
        "A58",
        "A57",
        "BF5",
        "A55",
        "BEF",
        "A56",
        "117A",
        "C24",
        "FF8"
      ]
    },
    "Bastion": {
      "sprays": [
        "26F",
        "600",
        "602",
        "603",
        "60B",
        "26B",
        "268",
        "605",
        "618",
        "606",
        "15A",
        "60A",
        "608",
        "26D",
        "265",
        "18B",
        "267",
        "269",
        "26E",
        "26C",
        "8DD",
        "266",
        "26A",
        "607",
        "15B8",
        "609",
        "B75",
        "C58",
        "D14",
        "D2F",
        "ED1",
        "EE2",
        "1078",
        "1169"
      ],
      "weapons": [
        "3B0",
        "3C5"
      ],
      "skins": [
        "46B",
        "46C",
        "46E",
        "46D",
        "46F",
        "471",
        "470",
        "C21",
        "C69",
        "E63",
        "FE8",
        "1533",
        "1882",
        "151F",
        "1881",
        "14F7",
        "187E",
        "147F",
        "1878",
        "13CC",
        "187F",
        "14A7",
        "187C",
        "14CF",
        "1879",
        "14E3",
        "187A",
        "1671",
        "168B",
        "150B",
        "1880",
        "1493",
        "187B",
        "146B",
        "1877",
        "14BB",
        "187D",
        "476",
        "475",
        "474",
        "477",
        "472",
        "12CE",
        "FE2"
      ],
      "poses": [
        "880",
        "5FD",
        "5FE",
        "5FF",
        "1242",
        "11B2",
        "C29",
        "F61"
      ],
      "highlight-intros": [
        "224",
        "13D",
        "13C",
        "13B",
        "1254"
      ],
      "voice-lines": [
        "61A",
        "61E",
        "620",
        "622",
        "A40",
        "8D0",
        "61C",
        "621",
        "61F",
        "15D3",
        "619",
        "61B",
        "121E",
        "BCF",
        "12B9",
        "C99",
        "133A",
        "D86",
        "1632",
        "F50",
        "10F4",
        "10F5",
        "1911",
        "110D",
        "110E"
      ],
      "emotes": [
        "8FD",
        "5FC",
        "BE5",
        "5FA",
        "BE6",
        "5FB",
        "B51",
        "FF9"
      ]
    },
    "Brigitte": {
      "weapons": [
        "16DA",
        "16DB"
      ],
      "sprays": [
        "16F9",
        "1703",
        "1705",
        "16FD",
        "1709",
        "16FB",
        "16F3",
        "1704",
        "1706",
        "1707",
        "1701",
        "16FF",
        "16E7",
        "16FC",
        "16F7",
        "1700",
        "16F4",
        "170A",
        "1702",
        "16FA",
        "16F5",
        "16F6",
        "16F8",
        "1708",
        "16FE",
        "18DD"
      ],
      "skins": [
        "1624",
        "16F1",
        "16EF",
        "16F0",
        "16EC",
        "16F2",
        "170D",
        "1740",
        "18F6",
        "173F",
        "18F5",
        "173C",
        "18F2",
        "1736",
        "18EC",
        "173D",
        "18F3",
        "1738",
        "18F0",
        "173A",
        "18ED",
        "173B",
        "18EE",
        "1741",
        "1742",
        "173E",
        "18F4",
        "1737",
        "18EF",
        "1735",
        "18EA",
        "1739",
        "18F1",
        "16B0",
        "1733",
        "1732",
        "16AE"
      ],
      "poses": [
        "1620",
        "1622",
        "1623",
        "1621",
        "1823"
      ],
      "highlight-intros": [
        "16D9",
        "16D1",
        "1722",
        "16D6"
      ],
      "voice-lines": [
        "16E1",
        "16E6",
        "16E0",
        "16E3",
        "16E4",
        "16E5",
        "16DD",
        "16DE",
        "16DF",
        "16E2",
        "16DC",
        "193E",
        "193D",
        "193F"
      ],
      "emotes": [
        "16D8",
        "1725",
        "1724",
        "174C",
        "16D5",
        "16EB"
      ]
    },
    "D.Va": {
      "sprays": [
        "1EC",
        "1099",
        "250",
        "15BC",
        "667",
        "66A",
        "671",
        "677",
        "1ED",
        "251",
        "673",
        "669",
        "676",
        "193",
        "24F",
        "670",
        "253",
        "1EE",
        "66C",
        "252",
        "668",
        "254",
        "66F",
        "256",
        "672",
        "255",
        "663",
        "B57",
        "C5C",
        "D17",
        "D33",
        "EE6",
        "ED6",
        "107A",
        "116D"
      ],
      "weapons": [
        "3AE",
        "3C3"
      ],
      "skins": [
        "4DD",
        "4DE",
        "4DF",
        "4E0",
        "4E1",
        "4E2",
        "4E3",
        "B28",
        "153B",
        "18AE",
        "1527",
        "18AD",
        "14FF",
        "18AA",
        "1487",
        "18A4",
        "13D6",
        "18AB",
        "14AF",
        "18A8",
        "14D7",
        "18A5",
        "14EB",
        "18A6",
        "1681",
        "1695",
        "1513",
        "18AC",
        "149B",
        "18A7",
        "1473",
        "18A3",
        "14C3",
        "18A9",
        "4E4",
        "12CD",
        "4E5",
        "4E6",
        "104E",
        "4E7",
        "CFF",
        "D26"
      ],
      "poses": [
        "87E",
        "65C",
        "65D",
        "65E",
        "C28",
        "D4C",
        "F17"
      ],
      "highlight-intros": [
        "22C",
        "153",
        "154",
        "155",
        "104B"
      ],
      "voice-lines": [
        "67E",
        "681",
        "A3C",
        "A3B",
        "67D",
        "67F",
        "67A",
        "680",
        "A3A",
        "8CE",
        "15D8",
        "679",
        "BD2",
        "1221",
        "C9E",
        "12BC",
        "D8A",
        "133E",
        "1637",
        "F54",
        "1915",
        "10C4",
        "10C3",
        "1115",
        "1116"
      ],
      "emotes": [
        "8FB",
        "BFB",
        "65B",
        "659",
        "65A",
        "D5D",
        "FFA",
        "BFC"
      ]
    },
    "Doomfist": {
      "weapons": [
        "119B",
        "119C"
      ],
      "sprays": [
        "11CA",
        "11C5",
        "15B6",
        "11C3",
        "11C2",
        "11C6",
        "11CF",
        "11BF",
        "11C9",
        "11C8",
        "11CE",
        "11D2",
        "11C7",
        "11CB",
        "11BC",
        "11C1",
        "11D1",
        "11CD",
        "11BE",
        "11D0",
        "1255",
        "11CC",
        "11C4",
        "1275",
        "11BD",
        "11C0",
        "1232",
        "12DC",
        "1392",
        "1391",
        "15E8",
        "15EB",
        "18DA"
      ],
      "skins": [
        "117D",
        "1181",
        "117F",
        "1180",
        "117E",
        "1183",
        "1182",
        "153E",
        "1869",
        "152A",
        "1868",
        "1502",
        "1865",
        "148A",
        "185F",
        "13D9",
        "1866",
        "14B2",
        "1863",
        "14DA",
        "1860",
        "14EE",
        "1861",
        "167B",
        "1698",
        "1516",
        "1867",
        "149E",
        "1862",
        "1476",
        "185E",
        "14C6",
        "1864",
        "117C",
        "1252",
        "117B",
        "1135",
        "1136",
        "1253"
      ],
      "poses": [
        "1190",
        "11FE",
        "1200",
        "11DC"
      ],
      "highlight-intros": [
        "1198",
        "118A",
        "1188",
        "118B",
        "1288"
      ],
      "voice-lines": [
        "119E",
        "11A4",
        "11A5",
        "11A6",
        "11A0",
        "11A3",
        "11A7",
        "11A2",
        "119A",
        "11A1",
        "15D1",
        "119F",
        "122C",
        "1230",
        "12CB",
        "12C8",
        "134A",
        "1349",
        "164C",
        "1630",
        "1939",
        "1937",
        "1938"
      ],
      "emotes": [
        "118E",
        "11A9",
        "120D",
        "11E1",
        "119D",
        "118D",
        "1282"
      ]
    },
    "Genji": {
      "sprays": [
        "72D",
        "15C2",
        "73F",
        "729",
        "727",
        "72F",
        "2D7",
        "2D1",
        "2DB",
        "192",
        "2D8",
        "2D9",
        "2D0",
        "C9D",
        "73E",
        "2D6",
        "73D",
        "2D5",
        "730",
        "728",
        "2D3",
        "2D4",
        "2D2",
        "72C",
        "72E",
        "73C",
        "72B",
        "B76",
        "C61",
        "D1E",
        "D3A",
        "EED",
        "ED4",
        "1085",
        "1174"
      ],
      "weapons": [
        "3B9",
        "3CE"
      ],
      "skins": [
        "490",
        "492",
        "494",
        "493",
        "491",
        "495",
        "496",
        "B26",
        "1463",
        "1906",
        "1462",
        "1905",
        "1460",
        "1902",
        "145A",
        "18FC",
        "13CF",
        "1903",
        "145C",
        "1900",
        "145E",
        "18FD",
        "145F",
        "18FE",
        "1674",
        "168E",
        "1461",
        "1904",
        "145B",
        "18FF",
        "1459",
        "18FB",
        "145D",
        "1901",
        "499",
        "49A",
        "C1F",
        "498",
        "497",
        "125F",
        "F91",
        "FE3"
      ],
      "poses": [
        "888",
        "7CC",
        "7A0",
        "7CD",
        "C89",
        "124B",
        "105A"
      ],
      "highlight-intros": [
        "22B",
        "152",
        "150",
        "151",
        "C43"
      ],
      "voice-lines": [
        "8D9",
        "A1B",
        "772",
        "A1C",
        "76E",
        "A1D",
        "76D",
        "15DF",
        "774",
        "A1E",
        "76F",
        "771",
        "BD9",
        "1228",
        "12C3",
        "CA5",
        "1345",
        "D91",
        "163E",
        "F5B",
        "10C5",
        "10C6",
        "191C",
        "1123",
        "1124"
      ],
      "emotes": [
        "906",
        "BEC",
        "7D0",
        "7CE",
        "BED",
        "7CF",
        "1212",
        "FE5"
      ]
    },
    "Hanzo": {
      "sprays": [
        "52C",
        "530",
        "531",
        "542",
        "1AB",
        "534",
        "52D",
        "53F",
        "1AC",
        "1A8",
        "186",
        "15B1",
        "532",
        "52B",
        "1AA",
        "1A5",
        "1A9",
        "1A4",
        "538",
        "1A3",
        "52A",
        "1AD",
        "52F",
        "1A6",
        "1A7",
        "1B0",
        "B77",
        "C53",
        "D0E",
        "D29",
        "EC5",
        "EDC",
        "1074",
        "1163"
      ],
      "weapons": [
        "3A9",
        "3BE"
      ],
      "skins": [
        "425",
        "426",
        "428",
        "427",
        "429",
        "42A",
        "42B",
        "C68",
        "1563",
        "17D0",
        "1560",
        "17CF",
        "155A",
        "17CC",
        "1548",
        "17C6",
        "13C6",
        "17CD",
        "154E",
        "17CA",
        "1554",
        "17C7",
        "1557",
        "17C8",
        "166C",
        "1685",
        "155D",
        "17CE",
        "154B",
        "17C9",
        "1545",
        "17C5",
        "1551",
        "17CB",
        "CB2",
        "42F",
        "42E",
        "42C",
        "42D",
        "1039",
        "128E",
        "F4A"
      ],
      "poses": [
        "879",
        "527",
        "529",
        "528",
        "11AD",
        "C30",
        "120C"
      ],
      "highlight-intros": [
        "21F",
        "12E",
        "12D",
        "12C",
        "113F"
      ],
      "voice-lines": [
        "8C9",
        "544",
        "548",
        "545",
        "546",
        "54A",
        "A2E",
        "A2D",
        "549",
        "54B",
        "521",
        "15CC",
        "1218",
        "BC9",
        "12B3",
        "C93",
        "D80",
        "1334",
        "162B",
        "E95",
        "10C8",
        "190B",
        "10C7",
        "1101",
        "1102"
      ],
      "emotes": [
        "8F6",
        "526",
        "524",
        "B29",
        "B2A",
        "525",
        "104C",
        "1093"
      ]
    },
    "Junkrat": {
      "sprays": [
        "210",
        "215",
        "5B2",
        "5C2",
        "5BF",
        "5B7",
        "214",
        "20E",
        "5AB",
        "5B3",
        "15B4",
        "191",
        "5A2",
        "20C",
        "217",
        "211",
        "5B8",
        "5B5",
        "5C1",
        "5B6",
        "20B",
        "20F",
        "216",
        "5B0",
        "213",
        "20D",
        "B55",
        "C55",
        "D11",
        "D2C",
        "EDF",
        "EC8",
        "1073",
        "1166"
      ],
      "weapons": [
        "3AC",
        "3C1"
      ],
      "skins": [
        "4B1",
        "4B3",
        "4B5",
        "4B4",
        "4B2",
        "12FA",
        "4B6",
        "4B7",
        "D55",
        "1458",
        "184B",
        "1457",
        "184A",
        "1455",
        "1847",
        "144F",
        "1841",
        "13D2",
        "1848",
        "1451",
        "1845",
        "1453",
        "1842",
        "1454",
        "1843",
        "1680",
        "1691",
        "1456",
        "1849",
        "1450",
        "1844",
        "144E",
        "1840",
        "1452",
        "1846",
        "4BB",
        "4B9",
        "4BA",
        "4B8",
        "106B",
        "C1D",
        "1251"
      ],
      "poses": [
        "87C",
        "5A8",
        "5A9",
        "5AA",
        "11AF",
        "1209",
        "C2E",
        "EC1",
        "17FA"
      ],
      "highlight-intros": [
        "22A",
        "14F",
        "14D",
        "14E",
        "B19"
      ],
      "voice-lines": [
        "5CB",
        "5C3",
        "5C4",
        "5C5",
        "15CF",
        "A09",
        "5C9",
        "5CA",
        "5C7",
        "A0A",
        "5C8",
        "8CC",
        "BCC",
        "121B",
        "C96",
        "12B6",
        "1337",
        "D83",
        "F4D",
        "162E",
        "10CA",
        "190E",
        "10C9",
        "1107",
        "1108"
      ],
      "emotes": [
        "8F9",
        "A89",
        "5A5",
        "A8A",
        "5A7",
        "5A6",
        "EB0",
        "10AB"
      ]
    },
    "Lúcio": {
      "sprays": [
        "5DE",
        "244",
        "5E7",
        "5DF",
        "15B5",
        "5DC",
        "5D7",
        "5ED",
        "246",
        "241",
        "5E9",
        "24C",
        "18F",
        "5E1",
        "249",
        "245",
        "247",
        "5DD",
        "24B",
        "248",
        "243",
        "242",
        "A48",
        "5E8",
        "5E4",
        "5E3",
        "BDE",
        "C56",
        "D12",
        "D2D",
        "EE0",
        "ED7",
        "1076",
        "1167"
      ],
      "weapons": [
        "3AD",
        "3C2"
      ],
      "skins": [
        "4D4",
        "4D8",
        "4D7",
        "4D6",
        "4D5",
        "4DA",
        "4D9",
        "CF7",
        "153A",
        "1858",
        "1526",
        "1857",
        "14FE",
        "1854",
        "1486",
        "184E",
        "13D5",
        "1855",
        "14AE",
        "1852",
        "14D6",
        "184F",
        "14EA",
        "1850",
        "1679",
        "1694",
        "1512",
        "1856",
        "149A",
        "1851",
        "1472",
        "184D",
        "14C2",
        "1853",
        "9EE",
        "1086",
        "4DC",
        "4DB",
        "9EF",
        "B4C",
        "B4D",
        "15F4",
        "FE9"
      ],
      "poses": [
        "87D",
        "5D4",
        "5D3",
        "5D2",
        "1280",
        "C7C",
        "1056"
      ],
      "highlight-intros": [
        "228",
        "147",
        "149",
        "148",
        "B17"
      ],
      "voice-lines": [
        "A0D",
        "15D0",
        "5F2",
        "5F3",
        "A0F",
        "A0E",
        "5F4",
        "A0B",
        "5F6",
        "8CD",
        "A0C",
        "5F7",
        "BCD",
        "121C",
        "C97",
        "12B7",
        "1338",
        "D84",
        "F4E",
        "162F",
        "10CB",
        "10CC",
        "190F",
        "1109",
        "110A"
      ],
      "emotes": [
        "8FA",
        "5D0",
        "A6B",
        "5CF",
        "A6A",
        "5D1",
        "B2C",
        "FE7"
      ]
    },
    "McCree": {
      "sprays": [
        "1B1",
        "55B",
        "556",
        "1B6",
        "1BA",
        "1B9",
        "558",
        "560",
        "1B5",
        "1B2",
        "1B8",
        "18C",
        "562",
        "554",
        "563",
        "1B7",
        "1BB",
        "1BE",
        "561",
        "55E",
        "55F",
        "555",
        "1B4",
        "15B2",
        "1B3",
        "568",
        "B54",
        "C54",
        "D2A",
        "D0F",
        "EC6",
        "EDD",
        "108F",
        "1164"
      ],
      "weapons": [
        "3AA",
        "3BF"
      ],
      "skins": [
        "4A6",
        "4AA",
        "4A8",
        "4A7",
        "4A9",
        "4AB",
        "12F8",
        "4AC",
        "B1D",
        "CFE",
        "1537",
        "1816",
        "1523",
        "1821",
        "14FB",
        "181E",
        "1483",
        "1818",
        "13D1",
        "181F",
        "14AB",
        "181C",
        "14D3",
        "1819",
        "14E7",
        "181A",
        "1676",
        "1690",
        "150F",
        "1820",
        "1497",
        "181B",
        "146F",
        "1817",
        "14BF",
        "181D",
        "4AF",
        "4AD",
        "4B0",
        "4AE",
        "10BF",
        "109C",
        "1250",
        "D05"
      ],
      "poses": [
        "87A",
        "553",
        "552",
        "551",
        "C26",
        "1577",
        "1058"
      ],
      "highlight-intros": [
        "225",
        "13E",
        "13F",
        "140",
        "1284"
      ],
      "voice-lines": [
        "15CD",
        "56D",
        "A3E",
        "573",
        "570",
        "575",
        "574",
        "572",
        "56F",
        "576",
        "8CA",
        "A3D",
        "1219",
        "BCA",
        "12B4",
        "C94",
        "D81",
        "1335",
        "E96",
        "162C",
        "10CD",
        "190C",
        "10CE",
        "1103",
        "1104"
      ],
      "emotes": [
        "8F7",
        "54E",
        "54F",
        "B78",
        "550",
        "B79",
        "D24",
        "CA9"
      ]
    },
    "Mei": {
      "sprays": [
        "63F",
        "63E",
        "1E8",
        "1E7",
        "25E",
        "25B",
        "A4A",
        "643",
        "264",
        "15B7",
        "62D",
        "25C",
        "638",
        "194",
        "262",
        "25D",
        "632",
        "639",
        "261",
        "62C",
        "263",
        "63C",
        "1E6",
        "25A",
        "25F",
        "260",
        "B74",
        "C57",
        "D2E",
        "D13",
        "EE1",
        "ED8",
        "1077",
        "1168"
      ],
      "weapons": [
        "3AF",
        "3C4"
      ],
      "skins": [
        "4E8",
        "4E9",
        "4EB",
        "4EC",
        "4EA",
        "4ED",
        "4EE",
        "153C",
        "1875",
        "1528",
        "1874",
        "1500",
        "1871",
        "1488",
        "186B",
        "13D7",
        "1872",
        "14B0",
        "186F",
        "14D8",
        "186C",
        "14EC",
        "186D",
        "1682",
        "1696",
        "1514",
        "1873",
        "149C",
        "186E",
        "1474",
        "186A",
        "14C4",
        "1870",
        "9F0",
        "1140",
        "4F0",
        "4EF",
        "9F1",
        "1194",
        "CF9",
        "D56",
        "E5D",
        "1383",
        "F79"
      ],
      "poses": [
        "87F",
        "62A",
        "629",
        "62B",
        "B5E",
        "C2D",
        "EB4"
      ],
      "highlight-intros": [
        "22D",
        "157",
        "156",
        "158",
        "C38"
      ],
      "voice-lines": [
        "64D",
        "64C",
        "646",
        "8CF",
        "A39",
        "A35",
        "A37",
        "64A",
        "15D2",
        "A38",
        "A36",
        "64B",
        "121D",
        "BCE",
        "12B8",
        "C98",
        "1339",
        "D85",
        "1631",
        "F4F",
        "1910",
        "10CF",
        "10D0",
        "110C",
        "110B"
      ],
      "emotes": [
        "8FC",
        "626",
        "AB0",
        "AB1",
        "628",
        "627",
        "113C",
        "D50",
        "EA5",
        "F5F"
      ]
    },
    "Mercy": {
      "sprays": [
        "50E",
        "519",
        "514",
        "198",
        "51F",
        "15B0",
        "195",
        "517",
        "19F",
        "518",
        "196",
        "197",
        "185",
        "1A0",
        "513",
        "508",
        "51A",
        "520",
        "19D",
        "1320",
        "1A2",
        "515",
        "19C",
        "50D",
        "50C",
        "19B",
        "199",
        "B53",
        "C51",
        "D28",
        "D0D",
        "EDB",
        "EC4",
        "1072",
        "1162"
      ],
      "weapons": [
        "3A8",
        "3BD"
      ],
      "skins": [
        "41A",
        "41B",
        "41E",
        "41D",
        "41C",
        "420",
        "41F",
        "B25",
        "D53",
        "152E",
        "17C4",
        "151A",
        "17C3",
        "14F2",
        "17C0",
        "147A",
        "17BA",
        "13C5",
        "17C1",
        "14A2",
        "17BE",
        "14CA",
        "17BB",
        "14DE",
        "17BC",
        "166B",
        "1684",
        "1506",
        "17C2",
        "148E",
        "17BD",
        "1466",
        "17B9",
        "14B6",
        "17BF",
        "423",
        "424",
        "422",
        "421",
        "1095",
        "B4F",
        "124F",
        "F8E"
      ],
      "poses": [
        "878",
        "4FD",
        "4FC",
        "4FB",
        "11AC",
        "C2B",
        "CF4",
        "123B"
      ],
      "highlight-intros": [
        "219",
        "128",
        "127",
        "126",
        "EAE"
      ],
      "voice-lines": [
        "502",
        "4FE",
        "A07",
        "8C8",
        "504",
        "506",
        "501",
        "15CB",
        "A08",
        "A05",
        "507",
        "A06",
        "BC8",
        "1217",
        "12B2",
        "C92",
        "1333",
        "D7F",
        "E94",
        "162A",
        "190A",
        "10D2",
        "10D1",
        "10FF",
        "1100"
      ],
      "emotes": [
        "8F5",
        "4F9",
        "4F8",
        "4FA",
        "1390",
        "A4E",
        "A4D",
        "CAA"
      ]
    },
    "Moira": {
      "weapons": [
        "12E7",
        "12E6"
      ],
      "sprays": [
        "1310",
        "1314",
        "1313",
        "130D",
        "1315",
        "1318",
        "1306",
        "1307",
        "15C8",
        "130B",
        "1304",
        "1319",
        "131B",
        "130C",
        "130F",
        "130E",
        "1309",
        "1316",
        "1305",
        "131E",
        "130A",
        "131D",
        "1311",
        "131C",
        "1308",
        "1317",
        "1396",
        "1395",
        "15EC",
        "15E7",
        "18DC"
      ],
      "skins": [
        "12FB",
        "1366",
        "1367",
        "1369",
        "1368",
        "136A",
        "136B",
        "153F",
        "18A1",
        "152B",
        "18A0",
        "1503",
        "189D",
        "148B",
        "1897",
        "13DC",
        "189E",
        "14B3",
        "189B",
        "14DB",
        "1898",
        "14EF",
        "1899",
        "167E",
        "169B",
        "1517",
        "189F",
        "149F",
        "189A",
        "1477",
        "1896",
        "14C7",
        "189C",
        "12F1",
        "137B",
        "138B",
        "12EE",
        "1386"
      ],
      "poses": [
        "12E9",
        "132C",
        "132E",
        "132D",
        "1822"
      ],
      "highlight-intros": [
        "12EA",
        "1353",
        "1324",
        "12FE"
      ],
      "voice-lines": [
        "135E",
        "15D7",
        "1355",
        "135B",
        "1358",
        "135D",
        "135C",
        "1356",
        "1359",
        "12EB",
        "135A",
        "1357",
        "134E",
        "134F",
        "164E",
        "1636",
        "193B",
        "193A",
        "193C"
      ],
      "emotes": [
        "12EC",
        "12FF",
        "1329",
        "15EF",
        "1351",
        "12ED",
        "1352"
      ]
    },
    "Orisa": {
      "sprays": [
        "100C",
        "100B",
        "1012",
        "100F",
        "1015",
        "100A",
        "1013",
        "1009",
        "1005",
        "1010",
        "1011",
        "1000",
        "1016",
        "1004",
        "15AF",
        "1002",
        "1007",
        "1003",
        "FFF",
        "1014",
        "1008",
        "100E",
        "1006",
        "100D",
        "1017",
        "1001",
        "1233",
        "12DF",
        "1394",
        "1393",
        "15E9",
        "15EA",
        "108E",
        "1161"
      ],
      "weapons": [
        "F69",
        "F6A"
      ],
      "skins": [
        "F67",
        "FED",
        "FEE",
        "FEF",
        "FF0",
        "FF1",
        "FEA",
        "1565",
        "1775",
        "1562",
        "1774",
        "155C",
        "1771",
        "154A",
        "176B",
        "13DB",
        "1772",
        "1550",
        "176F",
        "1556",
        "176C",
        "1559",
        "176D",
        "167D",
        "169A",
        "155F",
        "1773",
        "154D",
        "176E",
        "1547",
        "176A",
        "1553",
        "1770",
        "F74",
        "F72",
        "124E",
        "F75",
        "F73",
        "F71"
      ],
      "poses": [
        "F64",
        "1022",
        "1023",
        "FFE",
        "127F",
        "17AA"
      ],
      "highlight-intros": [
        "F65",
        "FF4",
        "FF2",
        "F90",
        "12A7"
      ],
      "voice-lines": [
        "1048",
        "1043",
        "1047",
        "1041",
        "F66",
        "1042",
        "1040",
        "103F",
        "1045",
        "1046",
        "1044",
        "15CA",
        "122E",
        "122F",
        "12C7",
        "12CA",
        "1348",
        "134B",
        "164D",
        "1629",
        "10D3",
        "10D4",
        "1909",
        "10FE",
        "10FD"
      ],
      "emotes": [
        "F63",
        "1049",
        "FEC",
        "FEB",
        "112B",
        "10F7",
        "1092",
        "1278"
      ]
    },
    "Pharah": {
      "sprays": [
        "2B4",
        "7B6",
        "7B1",
        "15C0",
        "7B4",
        "2B6",
        "7C1",
        "2B8",
        "2B5",
        "2B1",
        "7B2",
        "2B7",
        "7B7",
        "7C0",
        "2B3",
        "183",
        "2B0",
        "7AA",
        "2B2",
        "7B5",
        "2AF",
        "2BB",
        "7AF",
        "2AE",
        "2B9",
        "7B3",
        "B5A",
        "C5F",
        "D1B",
        "D37",
        "EEA",
        "ECC",
        "1090",
        "1171"
      ],
      "weapons": [
        "3B6",
        "3CB"
      ],
      "skins": [
        "448",
        "44A",
        "44C",
        "449",
        "44B",
        "89F",
        "8A0",
        "C6C",
        "CFB",
        "1437",
        "17F7",
        "1436",
        "17F6",
        "1434",
        "17F3",
        "142E",
        "17ED",
        "13C9",
        "17F4",
        "1430",
        "17F1",
        "1432",
        "17EE",
        "1433",
        "17EF",
        "166E",
        "1688",
        "1435",
        "17F5",
        "142F",
        "17F0",
        "142D",
        "17EC",
        "1431",
        "17F2",
        "E84",
        "453",
        "9ED",
        "454",
        "9EC",
        "44F",
        "120B",
        "CE7"
      ],
      "poses": [
        "885",
        "7A8",
        "7A7",
        "7A9",
        "B9E",
        "C42",
        "D07"
      ],
      "highlight-intros": [
        "21D",
        "85",
        "83",
        "84",
        "1141"
      ],
      "voice-lines": [
        "A12",
        "7CB",
        "7C5",
        "7C2",
        "A10",
        "A11",
        "7CA",
        "7C8",
        "8D6",
        "7C4",
        "7C9",
        "15DC",
        "1225",
        "BD6",
        "CA2",
        "12C0",
        "1342",
        "D8E",
        "F58",
        "163B",
        "10D5",
        "10D6",
        "1919",
        "111D",
        "111E"
      ],
      "emotes": [
        "903",
        "7A5",
        "AA8",
        "7A4",
        "7A6",
        "AA9",
        "1061",
        "FE6"
      ]
    },
    "Reaper": {
      "sprays": [
        "74B",
        "29F",
        "74A",
        "760",
        "751",
        "292",
        "294",
        "297",
        "757",
        "29A",
        "74E",
        "75F",
        "181",
        "29E",
        "761",
        "295",
        "299",
        "759",
        "298",
        "756",
        "749",
        "752",
        "15BE",
        "75A",
        "758",
        "29C",
        "293",
        "B58",
        "C5D",
        "D35",
        "D19",
        "EE8",
        "ECA",
        "1082",
        "116F"
      ],
      "weapons": [
        "3B4",
        "3C9"
      ],
      "skins": [
        "3F6",
        "3F8",
        "3F9",
        "3FA",
        "3F7",
        "3FB",
        "12AF",
        "3FC",
        "CFD",
        "152C",
        "1798",
        "1518",
        "1797",
        "14F0",
        "1794",
        "1478",
        "178E",
        "13C3",
        "1795",
        "14A0",
        "1792",
        "14C8",
        "178F",
        "14DC",
        "1790",
        "166A",
        "1683",
        "1504",
        "1796",
        "148C",
        "1791",
        "1464",
        "1782",
        "14B4",
        "1793",
        "404",
        "403",
        "407",
        "408",
        "405",
        "106A",
        "1193",
        "A86",
        "1385"
      ],
      "poses": [
        "884",
        "748",
        "741",
        "747",
        "1142",
        "B83",
        "C44"
      ],
      "highlight-intros": [
        "21B",
        "5D",
        "5B",
        "5C",
        "C33"
      ],
      "voice-lines": [
        "15DA",
        "762",
        "A2C",
        "764",
        "76B",
        "76A",
        "A29",
        "768",
        "769",
        "A2A",
        "A2B",
        "8D4",
        "BD4",
        "1223",
        "CA0",
        "12BE",
        "D8C",
        "1340",
        "1639",
        "F56",
        "10D7",
        "10D8",
        "1917",
        "111A",
        "1119"
      ],
      "emotes": [
        "901",
        "C01",
        "746",
        "1148",
        "744",
        "745",
        "C02",
        "E80"
      ]
    },
    "Reinhardt": {
      "sprays": [
        "278",
        "283",
        "282",
        "15BB",
        "279",
        "6EF",
        "27E",
        "277",
        "6D7",
        "6DD",
        "280",
        "27B",
        "27A",
        "184",
        "6DA",
        "276",
        "27C",
        "6DC",
        "6D9",
        "6EE",
        "27D",
        "6DE",
        "6D8",
        "27F",
        "6DB",
        "6DF",
        "B56",
        "C5A",
        "D16",
        "D32",
        "EE5",
        "ECD",
        "1079",
        "116C"
      ],
      "weapons": [
        "3B2",
        "3C7"
      ],
      "skins": [
        "43B",
        "43D",
        "43F",
        "43C",
        "43E",
        "447",
        "440",
        "C8A",
        "FD9",
        "1530",
        "17EB",
        "151C",
        "17EA",
        "14F4",
        "17E7",
        "147C",
        "17E1",
        "13C8",
        "17E8",
        "14A4",
        "17E5",
        "14CC",
        "17E2",
        "14E0",
        "17E3",
        "166D",
        "1687",
        "1508",
        "17E9",
        "1490",
        "17E4",
        "1468",
        "17E0",
        "14B8",
        "17E6",
        "A71",
        "444",
        "445",
        "FCE",
        "A72",
        "442",
        "443",
        "C1B"
      ],
      "poses": [
        "882",
        "6D5",
        "6D4",
        "6D6",
        "C27",
        "D08",
        "1744"
      ],
      "highlight-intros": [
        "21E",
        "88",
        "89",
        "87",
        "11BA"
      ],
      "voice-lines": [
        "A2F",
        "6F5",
        "6F9",
        "6F4",
        "6F2",
        "6F8",
        "6F0",
        "8D2",
        "6F6",
        "6F3",
        "6F7",
        "15D6",
        "BD1",
        "1220",
        "C9C",
        "12BB",
        "133D",
        "D89",
        "F53",
        "1635",
        "10D9",
        "1914",
        "10DA",
        "1114",
        "1113"
      ],
      "emotes": [
        "8FF",
        "6D1",
        "A82",
        "6D3",
        "A81",
        "6D2",
        "C2F",
        "CF5"
      ]
    },
    "Roadhog": {
      "sprays": [
        "8E0",
        "15BF",
        "795",
        "793",
        "78A",
        "788",
        "78B",
        "2A1",
        "78C",
        "2A6",
        "2A0",
        "2A8",
        "2A2",
        "792",
        "190",
        "78D",
        "785",
        "781",
        "2A7",
        "2AB",
        "794",
        "2A4",
        "787",
        "2A9",
        "2A5",
        "789",
        "B59",
        "C5E",
        "D1A",
        "D36",
        "EE9",
        "ED3",
        "1083",
        "1170"
      ],
      "weapons": [
        "3B5",
        "3CA"
      ],
      "skins": [
        "49B",
        "49C",
        "49D",
        "49E",
        "49F",
        "4A1",
        "4A0",
        "CFC",
        "1536",
        "18C8",
        "1522",
        "18C7",
        "14FA",
        "18C4",
        "1482",
        "18BE",
        "13D0",
        "18C5",
        "14AA",
        "18C2",
        "14D2",
        "18BF",
        "14E6",
        "18C0",
        "1675",
        "168F",
        "150E",
        "18C6",
        "1496",
        "18C1",
        "146E",
        "18BD",
        "14BE",
        "18C3",
        "125D",
        "4A5",
        "4A2",
        "4A3",
        "4A4",
        "A7C",
        "125E",
        "BEB"
      ],
      "poses": [
        "877",
        "77B",
        "77C",
        "77A",
        "B7F",
        "C34",
        "1249",
        "EC0",
        "17FC"
      ],
      "highlight-intros": [
        "229",
        "14B",
        "14A",
        "14C",
        "1185",
        "EAD"
      ],
      "voice-lines": [
        "A13",
        "15DB",
        "A16",
        "79F",
        "798",
        "799",
        "A14",
        "A15",
        "79D",
        "8D5",
        "79C",
        "79B",
        "1224",
        "BD5",
        "12BF",
        "CA1",
        "D8D",
        "1341",
        "163A",
        "F57",
        "10DB",
        "10DC",
        "1918",
        "111B",
        "111C"
      ],
      "emotes": [
        "902",
        "A52",
        "779",
        "777",
        "778",
        "A53",
        "127D",
        "10AC"
      ]
    },
    "Soldier: 76": {
      "sprays": [
        "7DE",
        "2BF",
        "7EE",
        "2C9",
        "2C4",
        "2C5",
        "7E6",
        "2C1",
        "2BD",
        "7DC",
        "18E",
        "2C3",
        "15C3",
        "2C8",
        "7E7",
        "2C0",
        "7F1",
        "7DF",
        "2BE",
        "2BC",
        "7E4",
        "2C2",
        "7E3",
        "7DB",
        "7D9",
        "2C7",
        "BA0",
        "C62",
        "D1C",
        "D38",
        "EEB",
        "ED5",
        "107F",
        "1172"
      ],
      "weapons": [
        "3B7",
        "3CC"
      ],
      "skins": [
        "4C7",
        "4CB",
        "4C8",
        "4C9",
        "4CA",
        "4CC",
        "4CD",
        "C71",
        "1539",
        "192A",
        "1525",
        "1929",
        "14FD",
        "1926",
        "1485",
        "1920",
        "13D4",
        "1927",
        "14AD",
        "1924",
        "14D5",
        "1921",
        "14E9",
        "1922",
        "1678",
        "1693",
        "1511",
        "1928",
        "1499",
        "1923",
        "1471",
        "1907",
        "14C1",
        "1925",
        "4D0",
        "4D2",
        "4D1",
        "4D3",
        "4CE",
        "1097",
        "1260",
        "D04"
      ],
      "poses": [
        "886",
        "7D8",
        "7D7",
        "7D6",
        "BAB",
        "C6F",
        "D51"
      ],
      "highlight-intros": [
        "227",
        "146",
        "128A",
        "144",
        "145"
      ],
      "voice-lines": [
        "7FB",
        "7F5",
        "7F8",
        "8D7",
        "A30",
        "7F6",
        "15DD",
        "7FA",
        "A32",
        "7F7",
        "A31",
        "7F9",
        "1226",
        "BD7",
        "CA3",
        "12C1",
        "1343",
        "D8F",
        "163C",
        "F59",
        "191A",
        "10DD",
        "10DE",
        "111F",
        "1120"
      ],
      "emotes": [
        "904",
        "BE1",
        "7D4",
        "7D5",
        "7D3",
        "BE2",
        "104D",
        "CF1"
      ]
    },
    "Sombra": {
      "sprays": [
        "CD7",
        "CDE",
        "CE2",
        "CCB",
        "CC9",
        "CE0",
        "CD9",
        "CCD",
        "CD4",
        "CDF",
        "CE3",
        "CD0",
        "CDD",
        "CD1",
        "CC8",
        "CCC",
        "15B9",
        "CCA",
        "CD6",
        "CE1",
        "CDC",
        "CDA",
        "CD5",
        "CD8",
        "CCF",
        "CD2",
        "CCE",
        "CDB",
        "CD3",
        "1234",
        "12DE",
        "D30",
        "D22",
        "EE3",
        "ED9",
        "107C",
        "116A"
      ],
      "weapons": [
        "AF0",
        "AF1"
      ],
      "skins": [
        "AE7",
        "AEA",
        "AEB",
        "AEC",
        "AED",
        "AE8",
        "AE9",
        "CF8",
        "153D",
        "1890",
        "1529",
        "188F",
        "1501",
        "188C",
        "1489",
        "1886",
        "13D8",
        "188D",
        "14B1",
        "188A",
        "14D9",
        "1887",
        "14ED",
        "1888",
        "167A",
        "1697",
        "1515",
        "188E",
        "149D",
        "1889",
        "1475",
        "1885",
        "14C5",
        "188B",
        "AF3",
        "AF5",
        "AF2",
        "AF4",
        "1096",
        "1257",
        "1258"
      ],
      "poses": [
        "AFA",
        "B12",
        "B10",
        "B11",
        "1243",
        "11B3",
        "127E",
        "EBE"
      ],
      "highlight-intros": [
        "AFB",
        "CC1",
        "B0F",
        "B0D"
      ],
      "voice-lines": [
        "E62",
        "B05",
        "B01",
        "AFF",
        "B04",
        "AFD",
        "15D4",
        "B00",
        "B06",
        "AFE",
        "B07",
        "B03",
        "B02",
        "122D",
        "1231",
        "12C9",
        "12CC",
        "133B",
        "D87",
        "F52",
        "1633",
        "1912",
        "10DF",
        "10E0",
        "110F",
        "1110"
      ],
      "emotes": [
        "AF6",
        "AF7",
        "10F8",
        "AF9",
        "1281",
        "AF8",
        "10F3",
        "1094"
      ]
    },
    "Symmetra": {
      "sprays": [
        "816",
        "812",
        "15C4",
        "818",
        "2DE",
        "810",
        "2E2",
        "2DF",
        "826",
        "815",
        "2E7",
        "18A",
        "1F8",
        "2E0",
        "2E1",
        "825",
        "819",
        "2E3",
        "823",
        "813",
        "824",
        "80F",
        "1F7",
        "1F9",
        "814",
        "817",
        "B5B",
        "C63",
        "D41",
        "D1F",
        "EEE",
        "ED0",
        "1081",
        "1175"
      ],
      "weapons": [
        "3BA",
        "3CF"
      ],
      "skins": [
        "478",
        "479",
        "47A",
        "47B",
        "47C",
        "12F0",
        "47D",
        "47E",
        "C6A",
        "D54",
        "1534",
        "1936",
        "1520",
        "1935",
        "14F8",
        "1932",
        "1480",
        "192C",
        "13CD",
        "1933",
        "14A8",
        "1930",
        "14D0",
        "192D",
        "14E4",
        "192E",
        "1672",
        "168C",
        "150C",
        "1934",
        "1494",
        "192F",
        "146C",
        "192B",
        "14BC",
        "1931",
        "484",
        "47F",
        "480",
        "483",
        "BEE",
        "FE4"
      ],
      "poses": [
        "889",
        "803",
        "7FC",
        "804",
        "11B8",
        "C7B",
        "1572",
        "105B"
      ],
      "highlight-intros": [
        "223",
        "138",
        "13A",
        "139",
        "D4D"
      ],
      "voice-lines": [
        "9F8",
        "9F5",
        "9F4",
        "80D",
        "9F9",
        "9F3",
        "9F6",
        "808",
        "8DA",
        "15E0",
        "9F7",
        "9F2",
        "BDA",
        "1229",
        "CA6",
        "12C4",
        "1346",
        "D92",
        "163F",
        "F5C",
        "10E2",
        "10E1",
        "191D",
        "1125",
        "1126"
      ],
      "emotes": [
        "907",
        "801",
        "7FD",
        "C04",
        "802",
        "C03",
        "B1C",
        "CF6"
      ]
    },
    "Torbjörn": {
      "sprays": [
        "2FD",
        "6AD",
        "300",
        "2FE",
        "6AB",
        "6BE",
        "2F8",
        "2FC",
        "1E9",
        "6BB",
        "6A9",
        "6A8",
        "187",
        "301",
        "2FB",
        "15BA",
        "6AC",
        "6BD",
        "6BF",
        "2FF",
        "2FA",
        "1EB",
        "6AF",
        "6A7",
        "6BC",
        "1EA",
        "BA2",
        "C59",
        "D31",
        "D15",
        "EE4",
        "ECE",
        "1091",
        "116B"
      ],
      "weapons": [
        "3B1",
        "3C6"
      ],
      "skins": [
        "430",
        "433",
        "431",
        "432",
        "434",
        "436",
        "435",
        "B27",
        "152F",
        "17DE",
        "151B",
        "17DD",
        "14F3",
        "17DA",
        "147B",
        "17D4",
        "13C7",
        "17DB",
        "14A3",
        "17D8",
        "14CB",
        "17D5",
        "14DF",
        "17D6",
        "167F",
        "1686",
        "1507",
        "17DC",
        "148F",
        "17D7",
        "1467",
        "17D3",
        "14B7",
        "17D9",
        "43A",
        "439",
        "438",
        "437",
        "1259",
        "109F",
        "C31",
        "103D",
        "F62"
      ],
      "voice-lines": [
        "9FE",
        "6C9",
        "6C6",
        "9FF",
        "8D1",
        "6C8",
        "6C3",
        "15D5",
        "6C0",
        "A00",
        "6C7",
        "9FD",
        "15E6",
        "15E5",
        "BD0",
        "121F",
        "12BA",
        "C9A",
        "133C",
        "D88",
        "1634",
        "F51",
        "1913",
        "10E4",
        "10E3",
        "1111",
        "1112"
      ],
      "poses": [
        "881",
        "6A4",
        "6A5",
        "6A6",
        "BC2",
        "C37",
        "D06"
      ],
      "highlight-intros": [
        "220",
        "131",
        "130",
        "12F",
        "104A"
      ],
      "emotes": [
        "8FE",
        "6A2",
        "6A3",
        "A7F",
        "6A1",
        "A80",
        "12A6",
        "E7F"
      ]
    },
    "Tracer": {
      "sprays": [
        "165",
        "173",
        "167",
        "E2",
        "873",
        "16F",
        "839",
        "15E",
        "169",
        "DF",
        "E0",
        "16E",
        "16C",
        "872",
        "170",
        "15C",
        "161",
        "168",
        "172",
        "178",
        "15C5",
        "16A",
        "171",
        "16B",
        "E1",
        "DE",
        "B5C",
        "C64",
        "D3C",
        "D20",
        "EEF",
        "EC9",
        "1080",
        "1176"
      ],
      "weapons": [
        "3BB",
        "3D0"
      ],
      "skins": [
        "409",
        "40D",
        "40C",
        "40A",
        "40B",
        "40E",
        "40F",
        "E54",
        "152D",
        "17A5",
        "1519",
        "17A4",
        "14F1",
        "17A1",
        "1479",
        "179B",
        "13C4",
        "17A2",
        "14A1",
        "179F",
        "14C9",
        "179C",
        "14DD",
        "179D",
        "1656",
        "1657",
        "1505",
        "17A3",
        "148D",
        "179E",
        "1465",
        "179A",
        "14B5",
        "17A0",
        "419",
        "410",
        "418",
        "411",
        "416",
        "B08",
        "B4A",
        "C32",
        "F77",
        "E7B"
      ],
      "emotes": [
        "908",
        "12AA",
        "82C",
        "10F6",
        "82D",
        "A54",
        "827",
        "1574",
        "1573",
        "A7E"
      ],
      "poses": [
        "876",
        "82E",
        "828",
        "82F",
        "11B9",
        "120A",
        "C50",
        "15F9"
      ],
      "highlight-intros": [
        "1FB",
        "51",
        "53",
        "52",
        "B18",
        "E4F"
      ],
      "voice-lines": [
        "A33",
        "A34",
        "832",
        "15E1",
        "835",
        "838",
        "836",
        "834",
        "831",
        "830",
        "8DB",
        "833",
        "BDB",
        "122A",
        "12C5",
        "CA7",
        "1347",
        "D93",
        "1640",
        "F5D",
        "10E5",
        "10E6",
        "191E",
        "1127",
        "1128"
      ]
    },
    "Widowmaker": {
      "sprays": [
        "2EF",
        "2EC",
        "2E8",
        "2F3",
        "695",
        "682",
        "2F2",
        "687",
        "693",
        "182",
        "698",
        "697",
        "685",
        "2F0",
        "683",
        "15C6",
        "8E1",
        "2EE",
        "699",
        "68A",
        "696",
        "2F4",
        "2EA",
        "688",
        "689",
        "2F1",
        "BDD",
        "C65",
        "D3F",
        "D23",
        "EF0",
        "ECB",
        "107D",
        "1177"
      ],
      "weapons": [
        "3BC",
        "3D1"
      ],
      "skins": [
        "460",
        "461",
        "463",
        "464",
        "462",
        "466",
        "465",
        "B24",
        "1532",
        "1781",
        "151E",
        "1780",
        "14F6",
        "177D",
        "147E",
        "1777",
        "13CB",
        "177E",
        "14A6",
        "177B",
        "14CE",
        "1778",
        "14E2",
        "1779",
        "1670",
        "168A",
        "150A",
        "177F",
        "1492",
        "177A",
        "146A",
        "1776",
        "14BA",
        "177C",
        "8A1",
        "8A2",
        "1264",
        "468",
        "467",
        "1263",
        "469",
        "1098",
        "1262",
        "103E"
      ],
      "poses": [
        "88A",
        "654",
        "655",
        "651",
        "BA3",
        "C36",
        "124D",
        "169C"
      ],
      "highlight-intros": [
        "21C",
        "12B",
        "12A",
        "129",
        "D43"
      ],
      "voice-lines": [
        "8DC",
        "69A",
        "6CB",
        "69D",
        "A04",
        "A03",
        "A02",
        "15E2",
        "6CE",
        "6CD",
        "6CC",
        "A01",
        "122B",
        "BDC",
        "12C6",
        "CA8",
        "D94",
        "1331",
        "1641",
        "F5E",
        "191F",
        "10E7",
        "10E8",
        "112A",
        "1129"
      ],
      "emotes": [
        "909",
        "A84",
        "652",
        "A83",
        "653",
        "650",
        "F60"
      ]
    },
    "Winston": {
      "sprays": [
        "1F5",
        "2CE",
        "1F1",
        "85F",
        "86C",
        "85A",
        "869",
        "85D",
        "1F4",
        "188",
        "1F0",
        "859",
        "84F",
        "1F6",
        "86B",
        "1F3",
        "2CF",
        "867",
        "85C",
        "2CA",
        "15C1",
        "1F2",
        "84C",
        "85E",
        "2CC",
        "85B",
        "BA1",
        "C60",
        "D39",
        "D1D",
        "EEC",
        "ECF",
        "1084",
        "1173"
      ],
      "weapons": [
        "3B8",
        "3CD"
      ],
      "skins": [
        "455",
        "456",
        "458",
        "457",
        "459",
        "45A",
        "45B",
        "1274",
        "1531",
        "18D4",
        "151D",
        "18D3",
        "14F5",
        "18D0",
        "147D",
        "18CA",
        "13CA",
        "18D1",
        "14A5",
        "18CE",
        "14CD",
        "18CB",
        "14E1",
        "18CC",
        "166F",
        "1689",
        "1509",
        "18D2",
        "1491",
        "18CD",
        "1469",
        "18C9",
        "14B9",
        "18CF",
        "45C",
        "45F",
        "45D",
        "45E",
        "BF1",
        "BF3",
        "142A"
      ],
      "poses": [
        "887",
        "84A",
        "849",
        "843",
        "B81",
        "C2C",
        "142B",
        "1059"
      ],
      "highlight-intros": [
        "221",
        "134",
        "133",
        "132",
        "1276"
      ],
      "voice-lines": [
        "A27",
        "8D8",
        "851",
        "15DE",
        "A26",
        "858",
        "A25",
        "A24",
        "855",
        "A28",
        "853",
        "857",
        "1227",
        "BD8",
        "12C2",
        "CA4",
        "D90",
        "1344",
        "163D",
        "F5A",
        "10E9",
        "10EA",
        "191B",
        "1121",
        "1122"
      ],
      "emotes": [
        "905",
        "BE7",
        "848",
        "847",
        "842",
        "BE8",
        "C25",
        "E81"
      ]
    },
    "Zarya": {
      "sprays": [
        "287",
        "715",
        "28A",
        "15BD",
        "289",
        "709",
        "291",
        "707",
        "719",
        "28F",
        "28E",
        "713",
        "703",
        "18D",
        "28D",
        "706",
        "71A",
        "286",
        "284",
        "70A",
        "288",
        "285",
        "28B",
        "28C",
        "290",
        "708",
        "BDF",
        "C5B",
        "D18",
        "D40",
        "ED2",
        "EE7",
        "107B",
        "116E"
      ],
      "weapons": [
        "3B3",
        "3C8"
      ],
      "skins": [
        "4BC",
        "4BE",
        "4C0",
        "4BF",
        "4BD",
        "4C1",
        "4C2",
        "CFA",
        "1538",
        "18BB",
        "1524",
        "18BA",
        "14FC",
        "18B7",
        "1484",
        "18B1",
        "13D3",
        "18B8",
        "14AC",
        "18B5",
        "14D4",
        "18B2",
        "14E8",
        "18B3",
        "1677",
        "1692",
        "1510",
        "18B9",
        "1498",
        "18B4",
        "1470",
        "18B0",
        "14C0",
        "18B6",
        "4C6",
        "125C",
        "4C4",
        "4C3",
        "4C5",
        "B30",
        "B4B",
        "BE9",
        "125B",
        "F7D"
      ],
      "poses": [
        "883",
        "6FF",
        "701",
        "700",
        "C45",
        "1247",
        "1570",
        "1057"
      ],
      "highlight-intros": [
        "226",
        "142",
        "143",
        "141",
        "126C"
      ],
      "voice-lines": [
        "15D9",
        "71C",
        "722",
        "A1A",
        "724",
        "723",
        "A17",
        "A18",
        "721",
        "8D3",
        "71F",
        "A19",
        "1222",
        "BD3",
        "12BD",
        "C9F",
        "133F",
        "D8B",
        "F55",
        "1638",
        "10EB",
        "10EC",
        "1916",
        "1118",
        "1117"
      ],
      "emotes": [
        "900",
        "6FD",
        "AAC",
        "6FE",
        "6FC",
        "AAD",
        "E82",
        "D02"
      ]
    },
    "Zenyatta": {
      "sprays": [
        "206",
        "203",
        "204",
        "201",
        "597",
        "591",
        "581",
        "58F",
        "585",
        "205",
        "1FE",
        "587",
        "589",
        "A41",
        "189",
        "15B3",
        "A4B",
        "20A",
        "1FF",
        "582",
        "58A",
        "596",
        "58C",
        "57F",
        "586",
        "208",
        "BE4",
        "C6E",
        "D2B",
        "D10",
        "EDE",
        "EC7",
        "1075",
        "1165"
      ],
      "weapons": [
        "3AB",
        "3C0"
      ],
      "skins": [
        "485",
        "489",
        "486",
        "487",
        "488",
        "48A",
        "12EF",
        "48B",
        "C6D",
        "1535",
        "183F",
        "1521",
        "183E",
        "14F9",
        "183B",
        "1481",
        "1835",
        "13CE",
        "183C",
        "14A9",
        "1839",
        "14D1",
        "1836",
        "14E5",
        "1837",
        "1673",
        "168D",
        "150D",
        "183D",
        "1495",
        "1838",
        "146D",
        "1834",
        "14BD",
        "183A",
        "48C",
        "48D",
        "48E",
        "48F",
        "1187",
        "A8D",
        "A87"
      ],
      "poses": [
        "87B",
        "57C",
        "57E",
        "57D",
        "B9D",
        "C2A",
        "123E"
      ],
      "highlight-intros": [
        "222",
        "136",
        "135",
        "137",
        "1060"
      ],
      "voice-lines": [
        "9FB",
        "59F",
        "9FC",
        "9FA",
        "15CE",
        "59D",
        "5A1",
        "59E",
        "5A0",
        "59A",
        "59B",
        "8CB",
        "121A",
        "BCB",
        "12B5",
        "C95",
        "1336",
        "D82",
        "F4C",
        "162D",
        "10EE",
        "10ED",
        "190D",
        "1105",
        "1106"
      ],
      "emotes": [
        "8F8",
        "579",
        "BF7",
        "57A",
        "57B",
        "BF6",
        "127C",
        "10AA"
      ]
    }
  },
  "shared-sprays": [
    "1E0",
    "1E1",
    "8DE",
    "8DF",
    "870",
    "1E2",
    "1D6",
    "1D2",
    "86E",
    "1E5",
    "1C4",
    "8E2",
    "1DD",
    "1D8",
    "8E4",
    "8E3",
    "8E5",
    "A8F",
    "C0D",
    "C8F",
    "C90",
    "105C",
    "11DA",
    "11DF",
    "138E",
    "1608",
    "1614",
    "126D",
    "169D",
    "172E",
    "A85",
    "C0E",
    "CF3",
    "1018",
    "105D",
    "11DB",
    "11E0",
    "138F",
    "1609",
    "1615",
    "126E",
    "169E",
    "172F",
    "C0A",
    "C07",
    "C09",
    "C08",
    "C06",
    "C05",
    "B9C",
    "1210",
    "120F",
    "120E",
    "CAB",
    "CAF",
    "CB0",
    "CAD",
    "12E2",
    "12E0",
    "12DD",
    "12E1",
    "D7D",
    "D78",
    "D7A",
    "D79",
    "13A3",
    "13A4",
    "F6B",
    "F6C",
    "10AE",
    "10AF",
    "10B0",
    "10B1",
    "10B2",
    "10B3",
    "18DB",
    "18DE",
    "18DF",
    "18E0",
    "18E1",
    "18E2",
    "1378",
    "1375",
    "1376",
    "1377",
    "16AB",
    "8D",
    "B13",
    "CEF",
    "15F1",
    "13FB",
    "13F9",
    "13F7",
    "13F5",
    "13F3",
    "13F1",
    "13EF",
    "13EC",
    "13EA",
    "13E5",
    "13E3",
    "13E7",
    "1BF",
    "1C0",
    "1C1",
    "1C2",
    "1C3",
    "1C5",
    "1C8",
    "1C9",
    "1CA",
    "1C7",
    "1D7",
    "1CC",
    "1DE",
    "1D0",
    "1DB",
    "1DC",
    "1D5",
    "1D4",
    "1C6",
    "90B",
    "1DA",
    "1D3",
    "871",
    "1D9",
    "1DF",
    "1E4",
    "86D",
    "125A",
    "C4B",
    "C4C",
    "C4D",
    "C4E",
    "C70",
    "C86",
    "C87",
    "C3A",
    "CAC",
    "CAE",
    "E52",
    "F6D",
    "EF1",
    "F4B",
    "F6F",
    "1650",
    "16A2",
    "10F1",
    "18EB",
    "1178"
  ],
  "player-icons": [
    "306",
    "82A",
    "82B",
    "15AC",
    "BC0",
    "D5F",
    "10BC",
    "115E",
    "30F",
    "7FF",
    "800",
    "15AB",
    "BBF",
    "12D3",
    "115D",
    "314",
    "775",
    "776",
    "15A6",
    "BBA",
    "C4A",
    "139D",
    "F06",
    "1158",
    "309",
    "7A2",
    "7A3",
    "15A7",
    "BBB",
    "1159",
    "30A",
    "6CF",
    "6D0",
    "15A2",
    "BB7",
    "F04",
    "10BB",
    "1154",
    "316",
    "725",
    "726",
    "C9B",
    "15A9",
    "BBE",
    "10B9",
    "115C",
    "312",
    "7D1",
    "7D2",
    "15AA",
    "BBC",
    "139E",
    "115A",
    "310",
    "5F8",
    "5F9",
    "15C7",
    "BB5",
    "139B",
    "1151",
    "CEC",
    "CED",
    "CEE",
    "15A0",
    "1236",
    "139C",
    "17B6",
    "1152",
    "305",
    "4F4",
    "4F3",
    "1597",
    "BAD",
    "C40",
    "10B8",
    "114A",
    "AE6",
    "ABB",
    "ABC",
    "1595",
    "BAC",
    "12D7",
    "1398",
    "10FA",
    "315",
    "5A3",
    "5A4",
    "159C",
    "BB0",
    "C41",
    "139A",
    "114E",
    "304",
    "54C",
    "54D",
    "159A",
    "BAE",
    "12D0",
    "164B",
    "10BE",
    "114C",
    "308",
    "64E",
    "64F",
    "15AD",
    "BC1",
    "164A",
    "10BD",
    "115F",
    "11D3",
    "11D4",
    "11D5",
    "159E",
    "1235",
    "17B4",
    "1321",
    "1322",
    "1323",
    "15AE",
    "17A9",
    "30B",
    "522",
    "523",
    "1598",
    "BC6",
    "1399",
    "17B3",
    "114B",
    "317",
    "657",
    "8BA",
    "109A",
    "15A3",
    "BB2",
    "F05",
    "1155",
    "16E8",
    "1717",
    "1718",
    "101C",
    "101D",
    "101E",
    "1596",
    "1237",
    "10B7",
    "1149",
    "311",
    "6FA",
    "6FB",
    "15A4",
    "BB8",
    "12D8",
    "1156",
    "30D",
    "845",
    "846",
    "15A8",
    "BBD",
    "D61",
    "F07",
    "17B5",
    "115B",
    "30E",
    "577",
    "578",
    "159B",
    "BAF",
    "12D4",
    "D62",
    "F03",
    "114D",
    "30C",
    "69F",
    "6A0",
    "15A1",
    "BB6",
    "12D2",
    "D60",
    "10BA",
    "1153",
    "307",
    "742",
    "743",
    "15A5",
    "BB9",
    "C3F",
    "12D1",
    "17B0",
    "1157",
    "313",
    "5CD",
    "5CE",
    "159D",
    "BB1",
    "17B1",
    "114F",
    "318",
    "624",
    "625",
    "159F",
    "BB3",
    "12D5",
    "F02",
    "17B2",
    "1150",
    "A90",
    "A92",
    "C0B",
    "C8C",
    "C8D",
    "105E",
    "11D8",
    "11DD",
    "138C",
    "1606",
    "160A",
    "126F",
    "169F",
    "1730",
    "A91",
    "C0C",
    "C8B",
    "C8E",
    "105F",
    "11D9",
    "11DE",
    "138D",
    "1607",
    "160F",
    "1270",
    "16A0",
    "1731",
    "C22",
    "BC4",
    "1239",
    "C39",
    "12DB",
    "D0C",
    "13A0",
    "D57",
    "164F",
    "10F2",
    "17A7",
    "113E",
    "1373",
    "1374",
    "16AC",
    "2F7",
    "2F9",
    "B14",
    "15F0",
    "1408",
    "1407",
    "1406",
    "1405",
    "1404",
    "1403",
    "1402",
    "1401",
    "1400",
    "13FF",
    "13FD",
    "13FE",
    "9D9",
    "9DC",
    "9E6",
    "8B8",
    "8B9",
    "9D3",
    "9D4",
    "9D5",
    "9D6",
    "9D7",
    "8BC",
    "8BB",
    "8C4",
    "8C5",
    "8C6",
    "8C7",
    "8F2",
    "8F3",
    "8F4",
    "8BD",
    "8BE",
    "8BF",
    "8C0",
    "8C1",
    "8C2",
    "8C3",
    "8E6",
    "9D8",
    "8E7",
    "9DA",
    "9DB",
    "9DD",
    "9DE",
    "8E8",
    "8EA",
    "8EB",
    "8EC",
    "8E9",
    "9DF",
    "9E0",
    "9E1",
    "9E2",
    "8ED",
    "9E3",
    "9E4",
    "9E5",
    "9E7",
    "8EE",
    "8EF",
    "9E8",
    "9E9",
    "9EA",
    "8F0",
    "8F1",
    "9EB",
    "B38",
    "B3B",
    "B3A",
    "B39",
    "B3C",
    "B3D",
    "B3E",
    "B3F",
    "B41",
    "B42",
    "B43",
    "B44",
    "B45",
    "B46",
    "B47",
    "B48",
    "B49",
    "C72",
    "C73",
    "C74",
    "C75",
    "C76",
    "C77",
    "C78",
    "C79",
    "C7A",
    "C7F",
    "C80",
    "C81",
    "C82",
    "12D9",
    "12DA",
    "D0A",
    "D63",
    "D64",
    "D65",
    "D66",
    "D67",
    "D68",
    "D69",
    "D6A",
    "D6B",
    "D6C",
    "D6D",
    "D6E",
    "D6F",
    "D70",
    "D71",
    "D72",
    "D73",
    "D74",
    "D75",
    "D76",
    "139F",
    "141D",
    "D58",
    "EF2",
    "EF3",
    "EF4",
    "EF5",
    "EF6",
    "EF7",
    "EF8",
    "EF9",
    "EFA",
    "EFB",
    "EFC",
    "EFD",
    "EFF",
    "F00",
    "F01",
    "16A1",
    "1642",
    "1643",
    "1644",
    "1645",
    "1646",
    "1647",
    "1648",
    "1649",
    "106C",
    "10B4",
    "10B5",
    "10B6",
    "17A8",
    "17AB",
    "17AC",
    "17AD",
    "17AE",
    "17AF",
    "1195"
  ]
}